{
  "id": "b-c-h",
  "type": "dog",
  "name": {
    "en": "Bắc Hà",
    "zh": "北河犬"
  },
  "images": [
    "https://cdn2.thedogapi.com/images/hOQCNqMDb.jpg"
  ],
  "origin": {
    "en": "Bắc Hà District, Lào Cai Province, northern Vietnam",
    "zh": "越南老街省北河县"
  },
  "history": {
    "en": "Indigenous spitz-type breed developed by ethnic minority groups, particularly the Hmong people, in the mountainous Bắc Hà region of northern Vietnam. Traditionally used for hunting, guarding, and companionship. Officially recognized by the Vietnam Kennel Association in 2019.",
    "zh": "本土斯皮茨型犬种，由越南北部北河山区的少数民族（尤其是苗族）培育。传统上用于狩猎、护卫和陪伴。2019年获得越南犬业协会正式认可。"
  },
  "stats": {
    "weight": {
      "male": "Male: 18-25; Female: 16-22",
      "female": "Male: 18-25; Female: 16-22"
    },
    "height": {
      "male": "Male: 46-56; Female: 41-51",
      "female": "Male: 46-56; Female: 41-51"
    },
    "lifespan": {
      "en": "12-15",
      "zh": "12-15"
    },
    "coatLength": {
      "en": "N/A",
      "zh": "N/A"
    },
    "colors": []
  },
  "traits": {
    "personality": 80,
    "temperament": 78,
    "loyalty": 74,
    "intelligence": 67,
    "friendliness": 93,
    "energy": 66
  },
  "health": {
    "shedding": {
      "en": "Moderate",
      "zh": "中等"
    },
    "sheddingLevel": 3,
    "diseases": [],
    "careTips": {
      "en": [
        "Regular veterinary checkups",
        "Proper nutrition"
      ],
      "zh": [
        "定期兽医检查",
        "合理饮食"
      ]
    }
  },
  "tags": [
    {
      "en": "Spitz and Primitive Types",
      "zh": "尖嘴犬和原始犬"
    },
    {
      "en": "Alert",
      "zh": "机警"
    },
    {
      "en": "loyal",
      "zh": "忠诚"
    },
    {
      "en": "intelligent",
      "zh": "聪明"
    },
    {
      "en": "protective",
      "zh": "保护欲"
    },
    {
      "en": "independent",
      "zh": "独立"
    }
  ]
}