{
  "id": "boston-terrier",
  "type": "dog",
  "name": {
    "en": "Boston Terrier",
    "zh": "Boston Terrier"
  },
  "images": [
    "https://cdn2.thedogapi.com/images/nwpd32sdl.jpg"
  ],
  "origin": {
    "en": "Boston, Massachusetts, United States",
    "zh": "Boston, Massachusetts, United States"
  },
  "history": {
    "en": "Developed in Boston in the 1870s from crossing English Bulldog with the now-extinct White English Terrier. Refined in the late 19th century and became one of the first American-developed breeds recognized by the AKC.",
    "zh": "Developed in Boston in the 1870s from crossing English Bulldog with the now-extinct White English Terrier. Refined in the late 19th century and became one of the first American-developed breeds recognized by the AKC."
  },
  "stats": {
    "weight": {
      "male": "5-11",
      "female": "5-11"
    },
    "height": {
      "male": "38-43",
      "female": "38-43"
    },
    "lifespan": {
      "en": "11-13",
      "zh": "11-13"
    },
    "coatLength": {
      "en": "N/A",
      "zh": "N/A"
    },
    "colors": []
  },
  "traits": {
    "personality": 88,
    "temperament": 87,
    "loyalty": 67,
    "intelligence": 82,
    "friendliness": 77,
    "energy": 78
  },
  "health": {
    "shedding": {
      "en": "Moderate",
      "zh": "中等"
    },
    "sheddingLevel": 3,
    "diseases": [],
    "careTips": {
      "en": [
        "Regular veterinary checkups",
        "Proper nutrition"
      ],
      "zh": [
        "定期兽医检查",
        "合理饮食"
      ]
    }
  },
  "tags": [
    {
      "en": "Non-Sporting",
      "zh": "Non-Sporting"
    },
    {
      "en": "Friendly",
      "zh": "Friendly"
    },
    {
      "en": "intelligent",
      "zh": "intelligent"
    },
    {
      "en": "outgoing",
      "zh": "outgoing"
    },
    {
      "en": "playful",
      "zh": "playful"
    }
  ]
}