{
  "id": "ragdoll",
  "type": "cat",
  "name": {
    "en": "Ragdoll",
    "zh": "Ragdoll"
  },
  "images": [
    "/images/breeds/cats/ragdoll-1.jpg"
  ],
  "origin": {
    "en": "United States",
    "zh": "United States"
  },
  "history": {
    "en": "Ragdolls love their people, greeting them at the door, following them around the house, and leaping into a lap or snuggling in bed whenever given the chance. They are the epitome of a lap cat, enjoy being carried and collapsing into the arms of anyone who holds them.",
    "zh": "Ragdolls love their people, greeting them at the door, following them around the house, and leaping into a lap or snuggling in bed whenever given the chance. They are the epitome of a lap cat, enjoy being carried and collapsing into the arms of anyone who holds them."
  },
  "stats": {
    "weight": {
      "male": "5 - 9",
      "female": "5 - 9"
    },
    "height": {
      "male": "N/A",
      "female": "N/A"
    },
    "lifespan": {
      "en": "12 - 17",
      "zh": "12 - 17"
    },
    "coatLength": {
      "en": "N/A",
      "zh": "N/A"
    },
    "colors": []
  },
  "traits": {
    "personality": 65,
    "temperament": 86,
    "loyalty": 67,
    "intelligence": 69,
    "friendliness": 74,
    "energy": 84
  },
  "health": {
    "shedding": {
      "en": "Moderate",
      "zh": "中等"
    },
    "sheddingLevel": 3,
    "diseases": [],
    "careTips": {
      "en": [
        "Regular veterinary checkups",
        "Proper nutrition and grooming"
      ],
      "zh": [
        "定期兽医检查",
        "合理饮食和梳理"
      ]
    }
  },
  "tags": [
    {
      "en": "Affectionate",
      "zh": "Affectionate"
    },
    {
      "en": "Friendly",
      "zh": "Friendly"
    },
    {
      "en": "Gentle",
      "zh": "Gentle"
    },
    {
      "en": "Quiet",
      "zh": "Quiet"
    },
    {
      "en": "Easygoing",
      "zh": "Easygoing"
    }
  ]
}